router.sv
`timescale 1ns / 1ps


module router
  (output reg [1:0] Port,
   input wire [1:0] p,				
   input wire [7:0] Address,
   input wire setup, reset, clk);
  
  wire found;
  wire [2:0] index;
  
  // the routing table consists of the address and port columns: 
  
  Addresses address_column 	(.found(found), .index(index),
                             .address_in(Address),
                            .setup(setup), .reset(reset), .clk(clk));
  
  Ports 	port_column 	(.port_out(Port),
                             .port_index(index), .p(p), .found(found),
                             .setup(setup), .reset(reset), .clk(clk)); 
  
endmodule

// the address column (8-bit shift register):

module Addresses
  (output reg found,
   output reg [2:0] index,
   input wire [7:0] address_in,
   input wire setup, reset, clk
   );
  
  reg [7:0] address [7:0];
      
  always @(posedge clk, posedge reset)
    begin
      if (reset) // asynchronous active HIGH reset
        begin
          address[0] <= 8'h00;
          address[0] <= 8'h00;
          address[2] <= 8'h00;
          address[3] <= 8'h00;
          address[4] <= 8'h00;
          address[5] <= 8'h00;
          address[6] <= 8'h00;
          address[7] <= 8'h00;
        end
      else if (setup == 1) //on the first phase (setup), fill the address column
        begin
          address[0] <= address_in;
          address[1] <= address[0];
          address[2] <= address[1];
          address[3] <= address[2];
          address[4] <= address[3];
          address[5] <= address[4];
          address[6] <= address[5];
          address[7] <= address[6];
        end
      else //setup 0, search for the input address
        case (address_in)
          address[0] : begin index <= 3'b000; found <= 1; end
          address[1] : begin index <= 3'b001; found <= 1; end
          address[2] : begin index <= 3'b010; found <= 1; end
          address[3] : begin index <= 3'b011; found <= 1; end
          address[4] : begin index <= 3'b100; found <= 1; end
          address[5] : begin index <= 3'b101; found <= 1; end
          address[6] : begin index <= 3'b110; found <= 1; end
          address[7] : begin index <= 3'b111; found <= 1; end
          default    : begin index <= 3'b000; found <= 0; end
        endcase
    end
          
endmodule
          
// the address column (2-bit shift register, 4 possiblem ports):
// (default port is 00) 

module Ports
  (output reg [1:0] port_out,
   input wire [2:0] port_index,
   input wire [1:0] p,
   input wire setup, reset, clk, found
   );
  
  reg [1:0] port [7:0];
 
  
  always @(posedge clk, posedge reset)
    begin
      if (reset) // asynchronous active HIGH reset
        begin
          port[0] <= 2'b00;
          port[1] <= 2'b00;
          port[2] <= 2'b00;
          port[3] <= 2'b00;
          port[4] <= 2'b00;
          port[5] <= 2'b00;
          port[6] <= 2'b00;
          port[7] <= 2'b00;
        end
      else if (setup == 1) //on the first phase (setup), fill the port column
        begin
          port[0] <= p;
          port[1] <= port[0];
          port[2] <= port[1];
          port[3] <= port[2];
          port[4] <= port[3];
          port[5] <= port[4];
          port[6] <= port[5];
          port[7] <= port[6];
        end
      else if (found == 1) //setup 0, search for the input address' destination 							 port
        port_out <= port[port_index];
      else  // found==0: route to default port (00)
		port_out <= 2'b00;
    end
          
endmodule

router_TB.sv
`timescale 1ns / 1ps


module Router_TB();
  
  reg [1:0] port;
  reg [1:0] p;
  reg [7:0] Address;
  reg setup, reset, clk;
  
  router router_DUT(.Port(port),
                    .p(p),
                    .Address(Address),
                    .setup(setup), .reset(reset), .clk(clk));
  
  initial begin
    $dumpfile("dump.vcd"); $dumpvars;
  end
  
  initial begin
    clk=0;
    forever
      #5 clk = ~clk;
  end
  	
 initial begin
    reset=0; setup=1; //fill the routing table:
   
    Address = 8'b0010_1010; p = 2'b10; #10
    Address = 8'b1101_1100; p = 2'b00; #10
    Address = 8'b1111_1001; p = 2'b01; #10
    Address = 8'b0010_1001; p = 2'b01; #10
    Address = 8'b1100_0110; p = 2'b10; #10
    Address = 8'b1101_1011; p = 2'b11; #10
    Address = 8'b1001_0011; p = 2'b00; #10
    Address = 8'b1010_1010; p = 2'b10; #11
    setup = 0; //begin routing:
   
   	Address = 8'hdb; #10
    Address = 8'h77; #13
    Address = 8'hc6; #17
    reset = 1'b1; #20
    $finish;    
  	end

endmodule

dump.vcd
$date
	Fri Sep 17 10:28:22 2021
$end
$version
	Icarus Verilog
$end
$timescale
	1ps
$end
$scope module Router_TB $end
$var wire 2 ! port [1:0] $end
$var reg 8 " Address [7:0] $end
$var reg 1 # clk $end
$var reg 2 $ p [1:0] $end
$var reg 1 % reset $end
$var reg 1 & setup $end
$scope module router_DUT $end
$var wire 8 ' Address [7:0] $end
$var wire 1 # clk $end
$var wire 2 ( p [1:0] $end
$var wire 1 % reset $end
$var wire 1 & setup $end
$var wire 3 ) index [2:0] $end
$var wire 1 * found $end
$var wire 2 + Port [1:0] $end
$scope module address_column $end
$var wire 8 , address_in [7:0] $end
$var wire 1 # clk $end
$var wire 1 % reset $end
$var wire 1 & setup $end
$var reg 1 * found $end
$var reg 3 - index [2:0] $end
$upscope $end
$scope module port_column $end
$var wire 1 # clk $end
$var wire 1 * found $end
$var wire 2 . p [1:0] $end
$var wire 3 / port_index [2:0] $end
$var wire 1 % reset $end
$var wire 1 & setup $end
$var reg 2 0 port_out [1:0] $end
$upscope $end
$upscope $end
$upscope $end
$enddefinitions $end
#0
$dumpvars
bx 0
bx /
b10 .
bx -
b101010 ,
bx +
x*
bx )
b10 (
b101010 '
1&
0%
b10 $
0#
b101010 "
bx !
$end
#5000
1#
#10000
0#
b0 $
b0 (
b0 .
b11011100 "
b11011100 '
b11011100 ,
#15000
1#
#20000
0#
b1 $
b1 (
b1 .
b11111001 "
b11111001 '
b11111001 ,
#25000
1#
#30000
0#
b101001 "
b101001 '
b101001 ,
#35000
1#
#40000
0#
b10 $
b10 (
b10 .
b11000110 "
b11000110 '
b11000110 ,
#45000
1#
#50000
0#
b11 $
b11 (
b11 .
b11011011 "
b11011011 '
b11011011 ,
#55000
1#
#60000
0#
b0 $
b0 (
b0 .
b10010011 "
b10010011 '
b10010011 ,
#65000
1#
#70000
0#
b10 $
b10 (
b10 .
b10101010 "
b10101010 '
b10101010 ,
#75000
1#
#80000
0#
#81000
b11011011 "
b11011011 '
b11011011 ,
0&
#85000
1*
b10 )
b10 -
b10 /
b0 !
b0 +
b0 0
1#
#90000
0#
#91000
b1110111 "
b1110111 '
b1110111 ,
#95000
b11 !
b11 +
b11 0
0*
b0 )
b0 -
b0 /
1#
#100000
0#
#104000
b11000110 "
b11000110 '
b11000110 ,
#105000
1*
b11 )
b11 -
b11 /
b0 !
b0 +
b0 0
1#
#110000
0#
#115000
b10 !
b10 +
b10 0
1#
#120000
0#
#121000
1%
